apps/__init__.py
apps/cli/__init__.py
apps/cli/main.py
apps/cli/simple_cli.py
apps/gui/__init__.py
apps/gui/main.py
apps/tui/__init__.py
apps/tui/main.py
killer_tools/__init__.py
killer_tools/core/__init__.py
killer_tools/core/logging.py
killer_tools/core/plugin.py
killer_tools/core/settings.py
killer_tools/core/theme.py
killer_tools/plugins/__init__.py
killer_tools/plugins/crypto/__init__.py
killer_tools/plugins/crypto/plugin.py
killer_tools/plugins/devtools/__init__.py
killer_tools/plugins/devtools/plugin.py
killer_tools/plugins/files/__init__.py
killer_tools/plugins/files/plugin.py
killertools-0.1.1.dist-info/entry_points.txt
killertools-0.1.1.dist-info/licenses/LICENSE
killertools-0.1.1.dist-info/METADATA
killertools-0.1.1.dist-info/WHEEL
killertools-0.1.1.dist-info/RECORD
