Metadata-Version: 2.4
Name: killertools
Version: 0.1.1
Summary: A modern, cross-platform Swiss-army toolkit for developers and makers
License: MIT
License-File: LICENSE
Keywords: cli,tui,gui,tools,utilities,developer,productivity
Author: Silas Renner (VoxHash)
Author-email: contact@voxhash.dev
Requires-Python: >=3.11,<3.14
Classifier: Development Status :: 4 - Beta
Classifier: Intended Audience :: Developers
Classifier: License :: OSI Approved :: MIT License
Classifier: Operating System :: OS Independent
Classifier: Programming Language :: Python :: 3
Classifier: Programming Language :: Python :: 3.11
Classifier: Programming Language :: Python :: 3.12
Classifier: Programming Language :: Python :: 3.13
Classifier: Topic :: Software Development :: Libraries :: Python Modules
Classifier: Topic :: System :: Systems Administration
Classifier: Topic :: Utilities
Provides-Extra: ai
Provides-Extra: network
Requires-Dist: PyQt6 (>=6.6.0,<7.0.0)
Requires-Dist: click (>=8.1.7,<9.0.0)
Requires-Dist: cryptography (>=41.0.0,<42.0.0)
Requires-Dist: openai (>=1.3.0,<2.0.0) ; extra == "ai"
Requires-Dist: pathlib2 (>=2.3.7,<3.0.0)
Requires-Dist: pillow (>=10.1.0,<11.0.0)
Requires-Dist: pydantic (>=2.5.0,<3.0.0)
Requires-Dist: pydantic-settings (>=2.1.0,<3.0.0)
Requires-Dist: pyjwt (>=2.8.0,<3.0.0)
Requires-Dist: python-dotenv (>=1.0.0,<2.0.0)
Requires-Dist: pyyaml (>=6.0.1,<7.0.0)
Requires-Dist: requests (>=2.31.0,<3.0.0)
Requires-Dist: rich (>=13.7.0,<14.0.0)
Requires-Dist: speedtest-cli (>=2.1.3,<3.0.0) ; extra == "network"
Requires-Dist: textual (>=0.44.0,<0.45.0)
Requires-Dist: toml (>=0.10.2,<0.11.0)
Requires-Dist: typer[all] (>=0.9.0,<0.10.0)
Requires-Dist: ulid-py (>=1.1.0,<2.0.0)
Requires-Dist: uuid (>=1.30,<2.0)
Project-URL: Documentation, https://voxhash.github.io/KillerTools
Project-URL: Homepage, https://github.com/VoxHash/KillerTools
Project-URL: Repository, https://github.com/VoxHash/KillerTools
